{
    "objects": [
        {
            "ID": "1",
            "Vorname": "Stella",
            "Nachname": "Griffiths",
            "Telefon": "1-675-380-6856"
        },
        {
            "ID": "2",
            "Vorname": "Celia",
            "Nachname": "Stewart",
            "Telefon": "4-052-058-6262"
        },
        {
            "ID": "3",
            "Vorname": "Jayden",
            "Nachname": "Rainford",
            "Telefon": "3-456-468-8821"
        },
        {
            "ID": "4",
            "Vorname": "Adelaide",
            "Nachname": "Wise",
            "Telefon": "7-271-538-6541"
        },
        {
            "ID": "5",
            "Vorname": "Agnes",
            "Nachname": "Patel",
            "Telefon": "7-271-538-6541"
        },
        {
            "ID": "6",
            "Vorname": "Josh",
            "Nachname": "Farrant",
            "Telefon": "3-123-834-5700"
        },
        {
            "ID": "7",
            "Vorname": "Manuel",
            "Nachname": "Hamilton",
            "Telefon": "5-218-888-8410"
        },
        {
            "ID": "8",
            "Vorname": "Josh",
            "Nachname": "Vernon",
            "Telefon": "7-508-160-7003"
        },
        {
            "ID": "9",
            "Vorname": "Elena",
            "Nachname": "Boyle",
            "Telefon": "1-017-283-1324"
        },
        {
            "ID": "10",
            "Vorname": "Andie",
            "Nachname": "Myatt",
            "Telefon": "7-271-538-6541"
        },
        {
            "ID": "11",
            "Vorname": "Henry",
            "Nachname": "Healy",
            "Telefon": "2-878-747-8021"
        },
        {
            "ID": "12",
            "Vorname": "Susan",
            "Nachname": "Downing",
            "Telefon": "6-511-565-4136"
        },
        {
            "ID": "13",
            "Vorname": "Johnathan",
            "Nachname": "Emmett",
            "Telefon": "4-416-683-7552"
        },
        {
            "ID": "14",
            "Vorname": "Elise",
            "Nachname": "Durrant",
            "Telefon": "5-031-546-4878"
        },
        {
            "ID": "15",
            "Vorname": "Jack",
            "Nachname": "Steer",
            "Telefon": "3-313-588-0701"
        },
        {
            "ID": "16",
            "Vorname": "Harvey",
            "Nachname": "Judd",
            "Telefon": "8-215-752-6535"
        },
        {
            "ID": "17",
            "Vorname": "Raquel",
            "Nachname": "Sawyer",
            "Telefon": "5-538-301-1728"
        },
        {
            "ID": "18",
            "Vorname": "Courtney",
            "Nachname": "Higgs",
            "Telefon": "5-283-535-8033"
        },
        {
            "ID": "19",
            "Vorname": "Marvin",
            "Nachname": "Cobb",
            "Telefon": "6-665-755-6825"
        },
        {
            "ID": "20",
            "Vorname": "Benjamin",
            "Nachname": "Gray",
            "Telefon": "3-480-501-4628"
        },
        {
            "ID": "21",
            "Vorname": "Nancy",
            "Nachname": "Speed",
            "Telefon": "8-378-281-5320"
        },
        {
            "ID": "22",
            "Vorname": "Sofia",
            "Nachname": "Selby",
            "Telefon": "8-828-028-6561"
        },
        {
            "ID": "23",
            "Vorname": "Jenna",
            "Nachname": "Dubois",
            "Telefon": "5-451-085-6474"
        },
        {
            "ID": "24",
            "Vorname": "Enoch",
            "Nachname": "Plumb",
            "Telefon": "4-047-520-5466"
        },
        {
            "ID": "25",
            "Vorname": "Bart",
            "Nachname": "Hastings",
            "Telefon": "7-576-448-4285"
        },
        {
            "ID": "26",
            "Vorname": "Kimberly",
            "Nachname": "Ianson",
            "Telefon": "4-605-800-4786"
        },
        {
            "ID": "27",
            "Vorname": "Joseph",
            "Nachname": "Niles",
            "Telefon": "4-504-050-4036"
        },
        {
            "ID": "28",
            "Vorname": "Megan",
            "Nachname": "Grant",
            "Telefon": "0-870-157-2457"
        },
        {
            "ID": "29",
            "Vorname": "Alan",
            "Nachname": "Bingham",
            "Telefon": "4-271-026-1675"
        },
        {
            "ID": "30",
            "Vorname": "Erin",
            "Nachname": "Lee",
            "Telefon": "6-677-217-1532"
        },
        {
            "ID": "31",
            "Vorname": "Bristol",
            "Nachname": "Collins",
            "Telefon": "3-857-852-0107"
        },
        {
            "ID": "32",
            "Vorname": "Nate",
            "Nachname": "Craig",
            "Telefon": "8-170-474-0251"
        },
        {
            "ID": "33",
            "Vorname": "Greta",
            "Nachname": "Fulton",
            "Telefon": "7-068-800-5827"
        },
        {
            "ID": "34",
            "Vorname": "Jamie",
            "Nachname": "Davies",
            "Telefon": "6-775-253-3842"
        },
        {
            "ID": "35",
            "Vorname": "Rocco",
            "Nachname": "Vane",
            "Telefon": "5-035-667-6216"
        },
        {
            "ID": "36",
            "Vorname": "Stephanie",
            "Nachname": "Flett",
            "Telefon": "3-026-533-0776"
        },
        {
            "ID": "37",
            "Vorname": "Cherish",
            "Nachname": "Carter",
            "Telefon": "4-358-218-0066"
        },
        {
            "ID": "38",
            "Vorname": "Shay",
            "Nachname": "Wise",
            "Telefon": "5-561-465-7347"
        },
        {
            "ID": "39",
            "Vorname": "Janelle",
            "Nachname": "Hogg",
            "Telefon": "4-607-328-0027"
        },
        {
            "ID": "40",
            "Vorname": "Sebastian",
            "Nachname": "Bryant",
            "Telefon": "6-864-202-7511"
        },
        {
            "ID": "41",
            "Vorname": "Tara",
            "Nachname": "Saunders",
            "Telefon": "1-464-578-8377"
        },
        {
            "ID": "42",
            "Vorname": "Gil",
            "Nachname": "Barrett",
            "Telefon": "0-825-360-5361"
        },
        {
            "ID": "43",
            "Vorname": "Hadley",
            "Nachname": "Harvey",
            "Telefon": "3-276-818-0086"
        },
        {
            "ID": "44",
            "Vorname": "Mike",
            "Nachname": "Brett",
            "Telefon": "0-551-020-5301"
        },
        {
            "ID": "45",
            "Vorname": "Jacob",
            "Nachname": "Collins",
            "Telefon": "4-438-376-4372"
        },
        {
            "ID": "46",
            "Vorname": "Emerald",
            "Nachname": "Seymour",
            "Telefon": "4-387-313-7885"
        },
        {
            "ID": "47",
            "Vorname": "Carolyn",
            "Nachname": "Nash",
            "Telefon": "8-520-183-2810"
        },
        {
            "ID": "48",
            "Vorname": "Matthew",
            "Nachname": "Asher",
            "Telefon": "3-676-285-1213"
        },
        {
            "ID": "49",
            "Vorname": "Hank",
            "Nachname": "Barclay",
            "Telefon": "1-322-551-6653"
        },
        {
            "ID": "50",
            "Vorname": "Violet",
            "Nachname": "Crawley",
            "Telefon": "7-265-473-5130"
        },
        {
            "ID": "51",
            "Vorname": "Kirsten",
            "Nachname": "Squire",
            "Telefon": "0-465-701-3260"
        },
        {
            "ID": "52",
            "Vorname": "Lexi",
            "Nachname": "Wallace",
            "Telefon": "8-658-681-0866"
        },
        {
            "ID": "53",
            "Vorname": "Carissa",
            "Nachname": "Graves",
            "Telefon": "5-314-648-2417"
        },
        {
            "ID": "54",
            "Vorname": "Kendra",
            "Nachname": "Clarke",
            "Telefon": "5-162-316-5260"
        },
        {
            "ID": "55",
            "Vorname": "Cameron",
            "Nachname": "Yarwood",
            "Telefon": "1-571-742-5111"
        },
        {
            "ID": "56",
            "Vorname": "Isabella",
            "Nachname": "Dale",
            "Telefon": "8-051-788-2703"
        },
        {
            "ID": "57",
            "Vorname": "Trisha",
            "Nachname": "Shields",
            "Telefon": "4-153-687-3538"
        },
        {
            "ID": "58",
            "Vorname": "Ron",
            "Nachname": "Clifford",
            "Telefon": "4-638-435-2071"
        },
        {
            "ID": "59",
            "Vorname": "Hazel",
            "Nachname": "Logan",
            "Telefon": "0-444-343-2685"
        },
        {
            "ID": "60",
            "Vorname": "Sonya",
            "Nachname": "King",
            "Telefon": "6-164-185-3783"
        },
        {
            "ID": "61",
            "Vorname": "Ron",
            "Nachname": "Robe",
            "Telefon": "0-672-180-1687"
        },
        {
            "ID": "62",
            "Vorname": "Makena",
            "Nachname": "Page ",
            "Telefon": "5-473-654-0372"
        },
        {
            "ID": "63",
            "Vorname": "Dani",
            "Nachname": "Sylvester",
            "Telefon": "7-703-040-7585"
        },
        {
            "ID": "64",
            "Vorname": "Shannon",
            "Nachname": "Anderson",
            "Telefon": "1-142-267-3302"
        },
        {
            "ID": "65",
            "Vorname": "Allison",
            "Nachname": "Wise",
            "Telefon": "0-744-134-0137"
        },
        {
            "ID": "66",
            "Vorname": "Emerald",
            "Nachname": "Shepherd",
            "Telefon": "0-744-134-0137"
        },
        {
            "ID": "67",
            "Vorname": "Barry",
            "Nachname": "Holt",
            "Telefon": "6-578-350-1625"
        },
        {
            "ID": "68",
            "Vorname": "Nick",
            "Nachname": "Driscoll",
            "Telefon": "6-810-846-5506"
        },
        {
            "ID": "69",
            "Vorname": "Bryon",
            "Nachname": "Shepherd",
            "Telefon": "1-087-374-8411"
        },
        {
            "ID": "70",
            "Vorname": "Hayden",
            "Nachname": "Donnelly",
            "Telefon": "4-681-827-3458"
        },
        {
            "ID": "71",
            "Vorname": "Bryon",
            "Nachname": "Donnelly",
            "Telefon": "6-500-042-1811"
        },
        {
            "ID": "72",
            "Vorname": "Britney",
            "Nachname": "Connor",
            "Telefon": "7-676-453-6806"
        },
        {
            "ID": "73",
            "Vorname": "Adeline",
            "Nachname": "Rycroft",
            "Telefon": "4-346-742-5571"
        },
        {
            "ID": "74",
            "Vorname": "Mandy",
            "Nachname": "Hunter",
            "Telefon": "7-482-501-0725"
        },
        {
            "ID": "75",
            "Vorname": "Oliver",
            "Nachname": "Gordon",
            "Telefon": "8-080-584-1468"
        },
        {
            "ID": "76",
            "Vorname": "Erick",
            "Nachname": "Egerton",
            "Telefon": "1-713-066-7176"
        },
        {
            "ID": "77",
            "Vorname": "Javier",
            "Nachname": "Allen",
            "Telefon": "2-608-238-8601"
        },
        {
            "ID": "78",
            "Vorname": "Johnathan",
            "Nachname": "Tait",
            "Telefon": "1-435-308-8566"
        },
        {
            "ID": "79",
            "Vorname": "Alison",
            "Nachname": "Rothwell",
            "Telefon": "5-705-373-3654"
        },
        {
            "ID": "80",
            "Vorname": "Sydney",
            "Nachname": "Sinclair",
            "Telefon": "4-385-003-2011"
        },
        {
            "ID": "81",
            "Vorname": "Gwenyth",
            "Nachname": "Funnell",
            "Telefon": "6-840-377-7842"
        },
        {
            "ID": "82",
            "Vorname": "Chelsea",
            "Nachname": "Hall",
            "Telefon": "1-564-135-7250"
        },
        {
            "ID": "83",
            "Vorname": "Chelsea",
            "Nachname": "Armstrong",
            "Telefon": "6-604-473-1122"
        },
        {
            "ID": "84",
            "Vorname": "Camila",
            "Nachname": "Watson",
            "Telefon": "7-127-808-0508"
        },
        {
            "ID": "85",
            "Vorname": "Mina",
            "Nachname": "Hall",
            "Telefon": "0-313-177-8136"
        },
        {
            "ID": "86",
            "Vorname": "Carolyn",
            "Nachname": "Hall",
            "Telefon": "4-852-221-2520"
        },
        {
            "ID": "87",
            "Vorname": "Jacqueline",
            "Nachname": "Carter",
            "Telefon": "7-271-538-6541"
        },
        {
            "ID": "88",
            "Vorname": "Julian",
            "Nachname": "Styles",
            "Telefon": "8-153-203-8330"
        },
        {
            "ID": "89",
            "Vorname": "Tyler",
            "Nachname": "Barclay",
            "Telefon": "1-082-347-7107"
        },
        {
            "ID": "90",
            "Vorname": "Judith",
            "Nachname": "Johnson",
            "Telefon": "4-133-114-6370"
        },
        {
            "ID": "91",
            "Vorname": "Tyler",
            "Nachname": "Johnson",
            "Telefon": "4-163-635-3751"
        },
        {
            "ID": "92",
            "Vorname": "Liam",
            "Nachname": "Pearce",
            "Telefon": "3-278-276-7547"
        },
        {
            "ID": "93",
            "Vorname": "Liam",
            "Nachname": "Miller",
            "Telefon": "7-145-730-1151"
        },
        {
            "ID": "94",
            "Vorname": "Esmeralda",
            "Nachname": "Miller",
            "Telefon": "1-082-347-7107"
        },
        {
            "ID": "95",
            "Vorname": "Phillip",
            "Nachname": "Andrews",
            "Telefon": "1-770-142-6853"
        },
        {
            "ID": "96",
            "Vorname": "Abdul",
            "Nachname": "Isaac",
            "Telefon": "1-082-347-7107"
        },
        {
            "ID": "97",
            "Vorname": "Johnathan",
            "Nachname": "Ainsworth",
            "Telefon": "2-411-543-5773"
        },
        {
            "ID": "98",
            "Vorname": "Kurt",
            "Nachname": "Murphy",
            "Telefon": "3-754-072-0286"
        },
        {
            "ID": "99",
            "Vorname": "Kieth",
            "Nachname": "Eddison",
            "Telefon": "7-861-230-1551"
        },
        {
            "ID": "100",
            "Vorname": "Kieth",
            "Nachname": "Eddison",
            "Telefon": "7-861-230-1551"
        }
    ]
}
